doc_models/__init__.py
doc_models/classification/__init__.py
doc_models/classification/detectron.py
doc_models/classification/scores.py
doc_models/clustering/__init__.py
doc_models/clustering/grid_opt.py
doc_models/clustering/horizontal.py
doc_models/clustering/spacing.py
doc_models/clustering/vertical.py
doc_models/components/__init__.py
doc_models/components/cluster.py
doc_models/components/document.py
doc_models/components/line_segment.py
doc_models/components/page.py
doc_models/components/word.py
doc_models/const.py
doc_models/images/__init__.py
doc_models/images/core.py
doc_models/images/filters.py
doc_models/ocr/ocr.ipynb
doc_models/ocr/tesseract.py
doc_models/poppler_load.py
doc_models/types.py
doc_models/utils.py
doc_models/visualization/__init__.py
doc_models/visualization/colors.py
doc_models/visualization/drawer.py
doc_models/visualization/impl/__init__.py
doc_models/visualization/impl/tesseract_data.py
doc_models/visualization/text.py
doc_models/visualization/tools/cli.py
doc_models/visualization/tools/draw.ipynb
doc_models/visualization/types.py
doc_models/visualization/utils.py
doc_models-0.1.0.dist-info/WHEEL
doc_models-0.1.0.dist-info/METADATA
doc_models-0.1.0.dist-info/RECORD
