Metadata-Version: 2.1
Name: doc-models
Version: 0.1.0
Summary: 
Author: Dan Kelleher
Author-email: kelleherjdan@gmail.com
Requires-Python: >=3.8,<4.0
Classifier: Programming Language :: Python :: 3
Classifier: Programming Language :: Python :: 3.10
Classifier: Programming Language :: Python :: 3.8
Classifier: Programming Language :: Python :: 3.9
Requires-Dist: Unidecode (>=1.3.6,<2.0.0)
Requires-Dist: opencv-python (>=4.6.0,<5.0.0)
Requires-Dist: pandas (>=1.5.1,<2.0.0)
Requires-Dist: pdf2image (>=1.16.0,<2.0.0)
Requires-Dist: pydantic (>=1.10.2,<2.0.0)
Requires-Dist: pytesseract (>=0.3.10,<0.4.0)
Requires-Dist: python-poppler (>=0.3.0,<0.4.0)
Requires-Dist: ready-logger (>=0.1.5,<0.2.0)
Requires-Dist: tqdm (>=4.64.1,<5.0.0)
